findthetail/__init__.py
findthetail/ftt.py
findthetail/teststatistics.py
findthetail/templates/report_base.html
findthetail-1.0.dist-info/METADATA
findthetail-1.0.dist-info/RECORD
findthetail-1.0.dist-info/WHEEL
findthetail-1.0.dist-info/top_level.txt
