Metadata-Version: 2.1
Name: findthetail
Version: 1.0
Summary: Package implementing the tail detection method detaild in the paper https://arxiv.org/abs/1805.10040.
Home-page: https://github.com/fstroth/findthetail
Author: Frederik Strothmann
Author-email: frstrothmann@gmail.com
License: MIT
Keywords: extreme value statistics tail detection
Platform: UNKNOWN
Classifier: Programming Language :: Python :: 3
Classifier: License :: OSI Approved :: Apache Software License
Classifier: Operating System :: OS Independent
